streamlit_bokeh_events/__init__.py
streamlit_bokeh_events/frontend/build/asset-manifest.json
streamlit_bokeh_events/frontend/build/bootstrap.min.css
streamlit_bokeh_events/frontend/build/index.html
streamlit_bokeh_events/frontend/build/precache-manifest.34a1c153056095acd6e93e463bd83b5f.js
streamlit_bokeh_events/frontend/build/precache-manifest.f645f80c42315c3252bfe1dc4cb12568.js
streamlit_bokeh_events/frontend/build/service-worker.js
streamlit_bokeh_events/frontend/build/static/js/2.5dec615c.chunk.js
streamlit_bokeh_events/frontend/build/static/js/2.5dec615c.chunk.js.LICENSE.txt
streamlit_bokeh_events/frontend/build/static/js/2.5dec615c.chunk.js.map
streamlit_bokeh_events/frontend/build/static/js/3.0bfdbef4.chunk.js
streamlit_bokeh_events/frontend/build/static/js/3.0bfdbef4.chunk.js.map
streamlit_bokeh_events/frontend/build/static/js/main.5184dd40.chunk.js
streamlit_bokeh_events/frontend/build/static/js/main.5184dd40.chunk.js.LICENSE.txt
streamlit_bokeh_events/frontend/build/static/js/main.5184dd40.chunk.js.map
streamlit_bokeh_events/frontend/build/static/js/main.67f64778.chunk.js
streamlit_bokeh_events/frontend/build/static/js/main.67f64778.chunk.js.LICENSE.txt
streamlit_bokeh_events/frontend/build/static/js/main.67f64778.chunk.js.map
streamlit_bokeh_events/frontend/build/static/js/runtime-main.06e5fdf4.js
streamlit_bokeh_events/frontend/build/static/js/runtime-main.06e5fdf4.js.map
streamlit_bokeh_events-0.1.2.dist-info/LICENSE
streamlit_bokeh_events-0.1.2.dist-info/METADATA
streamlit_bokeh_events-0.1.2.dist-info/WHEEL
streamlit_bokeh_events-0.1.2.dist-info/top_level.txt
streamlit_bokeh_events-0.1.2.dist-info/RECORD
